{
  "words": [
    {
      "originalLang": "en",
      "originalWord": "Hello",
      "translatedLang": "ar",
      "translatedWord": "مرحبا",
      "id": 8
    },
    {
      "originalLang": "es",
      "originalWord": "perro",
      "translatedLang": "fr",
      "translatedWord": "chien",
      "id": 9
    },
    {
      "originalLang": "it",
      "originalWord": "luche",
      "translatedLang": "es",
      "translatedWord": "♪",
      "id": 10
    },
    {
      "originalLang": "it",
      "originalWord": "luce",
      "translatedLang": "fr",
      "translatedWord": "lumière",
      "id": 11
    },
    {
      "originalLang": "de",
      "originalWord": "liebe",
      "translatedLang": "it",
      "translatedWord": "amore",
      "id": 12
    },
    {
      "originalLang": "fr",
      "originalWord": "chat",
      "translatedLang": "es",
      "translatedWord": "gato",
      "id": 13
    },
    {
      "originalLang": "it",
      "originalWord": "luce",
      "translatedLang": "fr",
      "translatedWord": "lumière",
      "id": 14
    },
    {
      "originalLang": "fr",
      "originalWord": "serpent",
      "translatedLang": "es",
      "translatedWord": "serpiente",
      "id": 15
    }
  ]
}